<?xml version="1.0" encoding="UTF-8"?>
<SaidaXml xmlns="Valim">
	<SaidaEmpresaId>OTICAAVE</SaidaEmpresaId>
	<SaidaId>1526</SaidaId>
	<SaidaDataEmissao>2020-08-11</SaidaDataEmissao>
	<SaidaData>2020-08-11</SaidaData>
	<SaidaClienteId>5077</SaidaClienteId>
	<SaidaValorServico>0.00</SaidaValorServico>
	<SaidaValorProduto>3690.00</SaidaValorProduto>
	<SaidaValorDesconto>38.00</SaidaValorDesconto>
	<SaidaValorICMSST>0.00</SaidaValorICMSST>
	<SaidaValorSeguro>0.00</SaidaValorSeguro>
	<SaidaValorOutrasDespesas>0.00</SaidaValorOutrasDespesas>
	<SaidaValorIPI>0.00</SaidaValorIPI>
	<SaidaValorFrete>0.00</SaidaValorFrete>
	<SaidaFreteEntraTotal>S</SaidaFreteEntraTotal>
	<SaidaXmlVendedor>
		<SaidaXmlVendedor>
			<SaidaVendedorEmpId>OTICAAVE</SaidaVendedorEmpId>
			<SaidaVendedorId>1</SaidaVendedorId>
		</SaidaXmlVendedor>
	</SaidaXmlVendedor>
</SaidaXml>
