<?xml version="1.0" encoding="utf-8"?>
<Dependencies type="guid" guid="2e31adc6-a329-8e94-5d3d-41917cedec66">
  <Table name="Classificacao" />
  <Table name="ClassificacaoOpcaoClassificacao" />
  <Table name="EnderecoPessoa" />
  <Table name="TelefonePessoa" />
  <Table name="Pessoa" />
  <Table name="PessoaClassificacao" />
  <Table name="Tabela" />
  <Table name="ParametroSistema" />
  <Table name="TipoCobranca" />
  <Table name="LogTabelaCampos" />
  <Table name="LogTabela" />
</Dependencies>