<?xml version="1.0" encoding="utf-8"?>
<Dependencies type="guid" guid="e12b05aa-2584-110d-0545-fda8caf4dbb8">
  <Table name="CentroCusto" />
  <Table name="Natureza" />
  <Table name="HistoricoCxaBco" />
  <Table name="TipoLancamento" />
  <Table name="ContaLancam" />
  <Table name="ContaRateio" />
  <Table name="LancamCxaBcoRateio" />
  <Table name="EstatisticaCentroCusto" />
  <Table name="TipoNatureza" />
  <Table name="Filial" />
  <Table name="ContaPagRec" />
  <Table name="LancamentoCxaBco" />
  <Table name="Tabela" />
  <Table name="ParametroSistema" />
</Dependencies>