<?xml version="1.0" encoding="utf-8"?>
<Dependencies type="guid" guid="f5495add-6ef7-dc22-2640-81370f15ad2d">
  <Table name="MenuNivel1" />
  <Table name="MenuNivel2" />
  <Table name="Programa" />
  <Table name="PermissaoUsuarioMenu" />
  <Table name="ProgramaUsuario" />
  <Table name="Sistema" />
  <Table name="Usuario" />
  <Table name="MenuNivel3" />
  <Table name="AtalhoSistema" />
  <Table name="Etiqueta" />
  <Table name="TipoPermissao" />
  <Table name="EtiquetaLinha" />
  <Table name="Grupo" />
  <Table name="PermissaoGrupoMenu" />
  <Table name="ProgramaGrupo" />
  <Table name="Tabela" />
  <Table name="Empresa" />
  <Table name="EmpresaSistemaEmpresa" />
  <Table name="UsuarioGrupo" />
  <Table name="AcessoSistema" />
</Dependencies>